bughunter_akabarki76-0.3.24.dist-info/licenses/LICENSE
bugster/__init__.py
bugster/analytics.py
bugster/cli.py
bugster/constants.py
bugster/types.py
bugster/analyzer/__init__.py
bugster/analyzer/main.py
bugster/analyzer/utils/__init__.py
bugster/analyzer/utils/analysis_tracker.py
bugster/analyzer/utils/assert_utils.py
bugster/analyzer/utils/errors.py
bugster/analyzer/utils/get_git_info.py
bugster/commands/__init__.py
bugster/commands/analyze.py
bugster/commands/auth.py
bugster/commands/destructive.py
bugster/commands/init.py
bugster/commands/issues.py
bugster/commands/middleware.py
bugster/commands/sync.py
bugster/commands/test.py
bugster/commands/update.py
bugster/utils/__init__.py
bugster/utils/colors.py
bugster/utils/console_messages.py
bugster/utils/file.py
bugster/utils/user_config.py
bugster/utils/yaml_spec.py
tests/__init__.py
tests/clients/__init__.py
tests/commands/__init__.py
tests/commands/test_sync.py
tests/commands/test_sync_metadata_consistency.py
tests/utils/__init__.py
tests/utils/test_yaml_spec.py
bughunter_akabarki76-0.3.24.dist-info/METADATA
bughunter_akabarki76-0.3.24.dist-info/WHEEL
bughunter_akabarki76-0.3.24.dist-info/entry_points.txt
bughunter_akabarki76-0.3.24.dist-info/top_level.txt
bughunter_akabarki76-0.3.24.dist-info/RECORD
