Metadata-Version: 2.4
Name: bughunter-akabarki76
Version: 0.3.24
Summary: A CLI tool for managing test cases
Author: akabarki76
Keywords: testing,cli,automation
Requires-Python: >=3.10
License-File: LICENSE
Requires-Dist: aiohappyeyeballs==2.6.1
Requires-Dist: aiohttp==3.11.18
Requires-Dist: aiosignal==1.3.2
Requires-Dist: altgraph==0.17.4
Requires-Dist: annotated-types==0.7.0
Requires-Dist: anyio==4.9.0
Requires-Dist: attrs==25.3.0
Requires-Dist: certifi==2025.6.15
Requires-Dist: charset-normalizer==3.4.2
Requires-Dist: click
Requires-Dist: gitdb==4.0.12
Requires-Dist: GitPython==3.1.44
Requires-Dist: loguru==0.7.3
Requires-Dist: macholib==1.16.3
Requires-Dist: h11==0.16.0
Requires-Dist: httpcore==1.0.9
Requires-Dist: httpx==0.28.1
Requires-Dist: httpx-sse==0.4.1
Requires-Dist: huggingface-hub==0.31.4
Requires-Dist: idna==3.10
Requires-Dist: markdown-it-py==3.0.0
Requires-Dist: MarkupSafe==3.0.2
Requires-Dist: mcp==1.10.0
Requires-Dist: mdurl==0.1.2
Requires-Dist: packaging==25.0
Requires-Dist: pathspec==0.12.1
Requires-Dist: posthog==5.0.0
Requires-Dist: pydantic==2.11.7
Requires-Dist: pydantic-settings==2.10.1
Requires-Dist: pydantic_core==2.33.2
Requires-Dist: Pygments==2.19.1
Requires-Dist: pyinstaller-hooks-contrib==2025.5
Requires-Dist: python-dotenv==1.1.1
Requires-Dist: python-multipart==0.0.20
Requires-Dist: PyYAML==6.0.2
Requires-Dist: referencing==0.36.2
Requires-Dist: regex==2024.11.6
Requires-Dist: requests==2.32.4
Requires-Dist: rich==14.0.0
Requires-Dist: rpds-py==0.25.1
Requires-Dist: shellingham==1.5.4
Requires-Dist: smmap==5.0.2
Requires-Dist: sniffio==1.3.1
Requires-Dist: sse-starlette==2.3.5
Requires-Dist: starlette==0.47.1
Requires-Dist: typer==0.15.4
Requires-Dist: types-requests==2.32.4.20250611
Requires-Dist: typing-inspection==0.4.1
Requires-Dist: typing_extensions==4.13.2
Requires-Dist: urllib3==2.5.0
Requires-Dist: uvicorn==0.35.0
Requires-Dist: websockets==15.0.1
Requires-Dist: yarl==1.20.0
Requires-Dist: zipp==3.23.0
Dynamic: author
Dynamic: description
Dynamic: description-content-type
Dynamic: keywords
Dynamic: license-file
Dynamic: requires-dist
Dynamic: requires-python
Dynamic: summary
